{"authorDailyContributionsMap":{"jenmarieng":[{"date":"2025-01-23","commitResults":[{"hash":"5521aca0e225f22f6814d212f3e2feb34c28d30e","isMergeCommit":false,"messageTitle":"Add level-0","messageBody":"","tags":["Level-0"],"fileTypesAndContributionMap":{"java":{"insertions":5,"deletions":10}}}]},{"date":"2025-01-30","commitResults":[{"hash":"7cc52f624680e305cf9876132853ec091927fac6","isMergeCommit":false,"messageTitle":"Add code to echo user commands and exit at bye","messageBody":"","fileTypesAndContributionMap":{"java":{"insertions":18,"deletions":1}}},{"hash":"cf41a963594ab1d80e8a8abf6c9862b7321fbc08","isMergeCommit":false,"messageTitle":"Update code to echo user commands and exit at bye","messageBody":"","tags":["Level-1"],"fileTypesAndContributionMap":{"java":{"insertions":7,"deletions":3}}},{"hash":"040e13900d48693e10e69be1f5ad3dbc566770ae","isMergeCommit":false,"messageTitle":"Add code to store and display a list of tasks","messageBody":"","tags":["Level-2"],"fileTypesAndContributionMap":{"java":{"insertions":18,"deletions":1}}},{"hash":"6933e497e1bd6a0effe5aad5042cf35c2fed3bef","isMergeCommit":false,"messageTitle":"Add TaskManager and Task classes to mark and unmark tasks","messageBody":"","tags":["Level-3","A-Classes"],"fileTypesAndContributionMap":{"java":{"insertions":90,"deletions":18}}}]},{"date":"2025-02-02","commitResults":[{"hash":"7d7bfdec06e7fcc2b98276d62a05340a682054a6","isMergeCommit":false,"messageTitle":"Modify code to adhere to coding standards","messageBody":"","tags":["A-CodingStandard"],"fileTypesAndContributionMap":{"java":{"insertions":12,"deletions":10}}}]},{"date":"2025-02-06","commitResults":[{"hash":"5286dc76416475cb6fc178c4f12c69ae4a91afdd","isMergeCommit":false,"messageTitle":"Add code to support 3 types of tasks","messageBody":"","tags":["Level-4"],"fileTypesAndContributionMap":{"java":{"insertions":104,"deletions":19}}},{"hash":"4ecad3233456ce8c9b342906f50acf42a996ff66","isMergeCommit":false,"messageTitle":"Edit the spacing for output of mark and unmark tasks","messageBody":"","fileTypesAndContributionMap":{"java":{"insertions":2,"deletions":2}}},{"hash":"d6a7a246534ff395466ff936f8a849836e3f55fa","isMergeCommit":false,"messageTitle":"Add code to semi-automate testing of Hachi","messageBody":"","tags":["A-TextUiTesting"],"fileTypesAndContributionMap":{"txt":{"insertions":10,"deletions":0},"bat":{"insertions":1,"deletions":1}}}]},{"date":"2025-02-07","commitResults":[{"hash":"10c875d7e18351baae0cb56ad468806ef60953e8","isMergeCommit":false,"messageTitle":"Edit code to improve code quality","messageBody":"","tags":["A-CodeQuality"],"fileTypesAndContributionMap":{"java":{"insertions":35,"deletions":21}}}]},{"date":"2025-02-12","commitResults":[{"hash":"6cffd9a43dcaeebb28d5c4b9986a8469f38558ef","isMergeCommit":false,"messageTitle":"Add exception handling for incorrect user inputs","messageBody":"","tags":["Level-5","A-Exceptions"],"fileTypesAndContributionMap":{"java":{"insertions":85,"deletions":51}}}]},{"date":"2025-02-14","commitResults":[{"hash":"0c30a5bf3fe90b3cb9d3b2235b636a7492a5e28c","isMergeCommit":false,"messageTitle":"Organise classes into relevant packages","messageBody":"","fileTypesAndContributionMap":{"java":{"insertions":17,"deletions":0}}},{"hash":"9513ffff8c88b06275271db1e87324a074ac81c8","isMergeCommit":true,"messageTitle":"Merge branch \u0027branch-A-Packages\u0027","messageBody":"","tags":["A-Packages"],"fileTypesAndContributionMap":{}}]},{"date":"2025-02-18","commitResults":[{"hash":"d6d67db112d3ecbac0fc78dc994ef5b1552c8536","isMergeCommit":false,"messageTitle":"Add code to support deleting of tasks","messageBody":"","fileTypesAndContributionMap":{"java":{"insertions":33,"deletions":17}}}]},{"date":"2025-02-19","commitResults":[{"hash":"7023dd9121531241080aafe61bd326ef7025d167","isMergeCommit":false,"messageTitle":"Implement saving of tasks in hard disk","messageBody":"","fileTypesAndContributionMap":{"txt":{"insertions":9,"deletions":0},"java":{"insertions":121,"deletions":15}}},{"hash":"9fa4467561ac64ff2bd4ff6c424fe57cbbb970ae","isMergeCommit":true,"messageTitle":"Merge branch \u0027branch-Level-6\u0027","messageBody":"","tags":["Level-6","A-Collections"],"fileTypesAndContributionMap":{}},{"hash":"a5adcda603aa0d4f01416cb0f9d4bd19e848ec69","isMergeCommit":true,"messageTitle":"Merge branch \u0027branch-Level-7\u0027","messageBody":"","tags":["Level-7"],"fileTypesAndContributionMap":{}},{"hash":"bc2d40a517819088be5521aef7d2a3f58d8932d1","isMergeCommit":false,"messageTitle":"Remove hard disk data and txt files","messageBody":"","fileTypesAndContributionMap":{"txt":{"insertions":0,"deletions":9}}}]},{"date":"2025-02-27","commitResults":[{"hash":"0d68d73b77c7df7ea3ee92e62cc846a920c6590d","isMergeCommit":false,"messageTitle":"Add more OOP and extract code as classes","messageBody":"","tags":["A-MoreOOP"],"fileTypesAndContributionMap":{"java":{"insertions":324,"deletions":111}}}]},{"date":"2025-03-05","commitResults":[{"hash":"002c6c565fa53d81b6e93554155d4f6411608ed3","isMergeCommit":false,"messageTitle":"Implement searching of tasks with a keyword","messageBody":"","fileTypesAndContributionMap":{"java":{"insertions":58,"deletions":3}}},{"hash":"3df18cdc7e0907ebfeb52946a4cc9524afd07c4b","isMergeCommit":false,"messageTitle":"Add JavaDoc comments to non-private classes and methods","messageBody":"","fileTypesAndContributionMap":{"java":{"insertions":112,"deletions":1}}},{"hash":"2a449c656275b6b2aeb61c88b4f27ea53adb3a23","isMergeCommit":true,"messageTitle":"Merge pull request #1 from jenmarieng/branch-Level-9","messageBody":"Implement searching of tasks with a keyword","tags":["Level-9"],"fileTypesAndContributionMap":{}},{"hash":"e0b72408d9e3e8b1193924303a7c015c2e557e8a","isMergeCommit":true,"messageTitle":"Merge branch \u0027master\u0027 into branch-A-JavaDoc","messageBody":"","tags":["A-JavaDoc"],"fileTypesAndContributionMap":{}},{"hash":"5f916e0e884cbb74f3c9eae6199f95355dbcb849","isMergeCommit":true,"messageTitle":"Merge pull request #2 from jenmarieng/branch-A-JavaDoc","messageBody":"Add JavaDoc comments to non-private classes and methods","fileTypesAndContributionMap":{}},{"hash":"43be8496924498c8cc185dca797679eba8da05d0","isMergeCommit":false,"messageTitle":"Update README.md","messageBody":"","tags":["A-UserGuide"],"fileTypesAndContributionMap":{"md":{"insertions":126,"deletions":14}}},{"hash":"b79536b66c56516feaf1da12c1ca60b650fd5209","isMergeCommit":false,"messageTitle":"Update README.md","messageBody":"","fileTypesAndContributionMap":{"md":{"insertions":5,"deletions":5}}},{"hash":"d3225cddc3c5a1de42f633c741f5fbfa61970f9e","isMergeCommit":false,"messageTitle":"Update README.md","messageBody":"","fileTypesAndContributionMap":{"md":{"insertions":0,"deletions":2}}},{"hash":"301be65435e8550ca1fe76afbc056d620d982ed8","isMergeCommit":false,"messageTitle":"Update README.md","messageBody":"","fileTypesAndContributionMap":{"md":{"insertions":4,"deletions":4}}}]}]},"authorFileTypeContributionMap":{"jenmarieng":{"java":770,"md":117,"fxml":0,"sh":0,"bat":1,"gradle":0,"txt":10}},"authorContributionVariance":{"jenmarieng":6392.867},"authorDisplayNameMap":{"jenmarieng":"CS2113-T13-3 NG D..AINE"}}
