{"authorDailyContributionsMap":{"venicephua":[{"date":"2025-01-23","commitResults":[{"hash":"fbda706981496ad5a0782bbf579a6513c06979ff","isMergeCommit":false,"messageTitle":"Renamed Chatbot, implemented greeting and exit","messageBody":"","tags":["Level-0"],"fileTypesAndContributionMap":{"java":{"insertions":32,"deletions":10},"bat":{"insertions":1,"deletions":1},"sh":{"insertions":1,"deletions":1},"md":{"insertions":1,"deletions":1}}}]},{"date":"2025-01-31","commitResults":[{"hash":"4032c6b70f64ad00fdafc8da1f8eff6f54b87e72","isMergeCommit":false,"messageTitle":"Implemented listen and echo","messageBody":"","tags":["Level-1"],"fileTypesAndContributionMap":{"java":{"insertions":36,"deletions":12}}}]},{"date":"2025-02-03","commitResults":[{"hash":"1d1ee1a76934c547de006216dcf07f8edddb6d38","isMergeCommit":false,"messageTitle":"Implemented a Task List to add tasks and list task items","messageBody":"","tags":["Level-2"],"fileTypesAndContributionMap":{"java":{"insertions":73,"deletions":22}}},{"hash":"a689ab954dfc978dc58218587f113af5049e309a","isMergeCommit":false,"messageTitle":"Implemented Mark/Unmark tasks as done","messageBody":"","tags":["Level-3","A-CodingStandard"],"fileTypesAndContributionMap":{"java":{"insertions":67,"deletions":28}}}]},{"date":"2025-02-07","commitResults":[{"hash":"c3012c8a211b3327ce84904219e990be35c5784b","isMergeCommit":false,"messageTitle":"Implemented Todo, Deadline, Event tasks","messageBody":"","tags":["Level-4"],"fileTypesAndContributionMap":{"java":{"insertions":157,"deletions":84}}},{"hash":"43d94aec997fb0401704a5b908979018168829d9","isMergeCommit":false,"messageTitle":"Refactored code and improved readability","messageBody":"","fileTypesAndContributionMap":{"java":{"insertions":35,"deletions":21}}},{"hash":"3abd36fb6284fb81e5627ae7d040664c2a4ea70f","isMergeCommit":false,"messageTitle":"Refactored code and improved readability","messageBody":"","tags":["A-CodeQuality"],"fileTypesAndContributionMap":{"java":{"insertions":0,"deletions":2}}}]},{"date":"2025-02-13","commitResults":[{"hash":"bfc4fe54b154e10ef56beec858ef8a0f07ba595c","isMergeCommit":false,"messageTitle":"Implemented Exceptions for Error Handling","messageBody":"","fileTypesAndContributionMap":{"java":{"insertions":172,"deletions":101}}}]},{"date":"2025-02-14","commitResults":[{"hash":"55e72db8bb89f0dcae1ba463917bf2ebd3ca13a5","isMergeCommit":false,"messageTitle":"Improved on Exceptions","messageBody":"","fileTypesAndContributionMap":{"java":{"insertions":15,"deletions":9}}},{"hash":"9b86c2628721b071242ce08869948309e6d566b9","isMergeCommit":false,"messageTitle":"Improved on Exceptions v2","messageBody":"","fileTypesAndContributionMap":{"java":{"insertions":1,"deletions":1}}},{"hash":"2f6723f73d5234d24600b8fd5718e324d95b0d67","isMergeCommit":false,"messageTitle":"Improved code cohesiveness","messageBody":"","fileTypesAndContributionMap":{"java":{"insertions":6,"deletions":6}}},{"hash":"e60d0a75e33a2f8b3872520a55615701a49e3c1f","isMergeCommit":true,"messageTitle":"Merge branch \u0027branch-Level-5\u0027 Implemented Exceptions for Error Handling","messageBody":"","tags":["Level-5","A-Exceptions"],"fileTypesAndContributionMap":{}},{"hash":"b7aa35a68e928ed177388e6128bdbe425f0e8c9f","isMergeCommit":false,"messageTitle":"Implemented Packages","messageBody":"","fileTypesAndContributionMap":{"java":{"insertions":25,"deletions":0}}},{"hash":"8a88f77f1f54a7ecc53184a6a7bcf14429ee6f22","isMergeCommit":true,"messageTitle":"Merge branch \u0027branch-A-Packages\u0027 Implemented Packages","messageBody":"","tags":["A-Packages"],"fileTypesAndContributionMap":{}}]},{"date":"2025-02-17","commitResults":[{"hash":"edd428268e8d6504b761394777540066d091816d","isMergeCommit":false,"messageTitle":"Implemented Delete and Clear tasks","messageBody":"","fileTypesAndContributionMap":{"java":{"insertions":127,"deletions":85}}}]},{"date":"2025-02-20","commitResults":[{"hash":"7befd10476b672b1600dea92854f0359c4dd3e85","isMergeCommit":false,"messageTitle":"Implemented Save","messageBody":"","fileTypesAndContributionMap":{"txt":{"insertions":6,"deletions":0},"java":{"insertions":235,"deletions":89}}},{"hash":"6cecb2f12661c3c26084e3472924986553c18b6f","isMergeCommit":true,"messageTitle":"Merge branch \u0027branch-Level-6\u0027 Merge branch \u0027branch-Level-6\u0027","messageBody":"","tags":["Level-6","A-Collections"],"fileTypesAndContributionMap":{}},{"hash":"60267115536db7fa6644ad593fb7ca148b0bf399","isMergeCommit":true,"messageTitle":"Implemented Save","messageBody":"","fileTypesAndContributionMap":{}},{"hash":"c0f54a5df72196226d3022b93e354fd7f69c734c","isMergeCommit":false,"messageTitle":"Cleaned up code","messageBody":"","fileTypesAndContributionMap":{"java":{"insertions":12,"deletions":7}}},{"hash":"c643bd1ad2b8f20b2982790a0bd57504d59eb5ea","isMergeCommit":true,"messageTitle":"Merge branch \u0027branch-Level-7\u0027","messageBody":"","fileTypesAndContributionMap":{}}]},{"date":"2025-02-21","commitResults":[{"hash":"26191278de4b171d123bce88fbb275a3073e98dd","isMergeCommit":false,"messageTitle":"Updated Save to delete and clear tasks","messageBody":"","tags":["Level-7"],"fileTypesAndContributionMap":{"java":{"insertions":3,"deletions":0}}}]}]},"authorFileTypeContributionMap":{"venicephua":{"java":518,"md":1,"fxml":0,"sh":1,"bat":1,"gradle":0,"txt":6}},"authorContributionVariance":{"venicephua":7536.667},"authorDisplayNameMap":{"venicephua":"PHUA..NICE"}}
